Metadata-Version: 2.4
Name: random-allocation
Version: 1.0.0
Summary: Tools for analyzing and comparing different sampling schemes in differential privacy
Author-email: Moshe Shenfeld <mosheshenfeld@gmail.com>
License: MIT
Project-URL: Homepage, https://github.com/moshenfeld/random_allocation
Project-URL: Bug Tracker, https://github.com/moshenfeld/random_allocation/issues
Keywords: differential-privacy,random-allocation,privacy-analysis
Classifier: Development Status :: 5 - Production/Stable
Classifier: Intended Audience :: Science/Research
Classifier: License :: OSI Approved :: MIT License
Classifier: Programming Language :: Python :: 3
Classifier: Programming Language :: Python :: 3.8
Classifier: Programming Language :: Python :: 3.9
Classifier: Programming Language :: Python :: 3.10
Classifier: Programming Language :: Python :: 3.11
Classifier: Programming Language :: Python :: 3.12
Classifier: Topic :: Scientific/Engineering :: Mathematics
Requires-Python: >=3.8
License-File: LICENSE
Requires-Dist: dp_accounting>=0.5.0
Requires-Dist: PLD_subsampling>=0.1.2
Requires-Dist: numpy<2.2,>=1.20.0
Requires-Dist: scipy>=1.7.0
Requires-Dist: matplotlib>=3.4.0
Requires-Dist: numba>=0.60.0
Provides-Extra: dev
Requires-Dist: pytest>=6.0; extra == "dev"
Requires-Dist: black>=21.0; extra == "dev"
Requires-Dist: flake8>=3.9; extra == "dev"
Requires-Dist: mypy>=1.0.0; extra == "dev"
Requires-Dist: types-setuptools; extra == "dev"
Provides-Extra: examples
Requires-Dist: ipykernel; extra == "examples"
Dynamic: license-file
